{
  "timestamp": "2025-06-22T04:46:16.780851",
  "components": {
    "Core Imports": {
      "status": "\u274c FAILED",
      "error": "No module named 'think_ai.storage.distributed.redis_cache'"
    },
    "Engine Initialization": {
      "status": "\u274c FAILED",
      "error": "Config.__init__() got an unexpected keyword argument 'model_name'"
    },
    "API Endpoints": {
      "status": "\u274c FAILED",
      "error": "No module named 'think_ai.storage.distributed.redis_cache'"
    },
    "Vector Search": {
      "status": "\u274c FAILED",
      "error": "create_vector_db() got an unexpected keyword argument 'backend'"
    },
    "Language Capabilities": {
      "status": "\u274c FAILED",
      "error": "GenerationConfig.__init__() got an unexpected keyword argument 'max_tokens'"
    },
    "Webapp Files": {
      "status": "\u2705 WORKING",
      "details": {
        "webapp_files": 25373,
        "nextjs_files": [
          "webapp/package.json",
          "webapp/next.config.js",
          "webapp/server.js"
        ],
        "webapp_exists": true
      }
    },
    "Full System Integration": {
      "status": "\u2705 WORKING",
      "details": {
        "error": "cannot import name 'ThinkAI' from 'think_ai' (/Users/champi/Development/Think_AI/think_ai/__init__.py)"
      }
    }
  },
  "capabilities": {},
  "errors": [
    "Core Imports: No module named 'think_ai.storage.distributed.redis_cache'",
    "Engine Initialization: Config.__init__() got an unexpected keyword argument 'model_name'",
    "API Endpoints: No module named 'think_ai.storage.distributed.redis_cache'",
    "Vector Search: create_vector_db() got an unexpected keyword argument 'backend'",
    "Language Capabilities: GenerationConfig.__init__() got an unexpected keyword argument 'max_tokens'"
  ],
  "summary": {
    "total_components": 7,
    "working_components": 2,
    "success_rate": "28.6%",
    "deployment_status": "PARTIAL"
  }
}